cli.py
link.py
github_to_colab_link-1.0.1.dist-info/LICENSE
github_to_colab_link-1.0.1.dist-info/METADATA
github_to_colab_link-1.0.1.dist-info/WHEEL
github_to_colab_link-1.0.1.dist-info/entry_points.txt
github_to_colab_link-1.0.1.dist-info/top_level.txt
github_to_colab_link-1.0.1.dist-info/RECORD
