Metadata-Version: 2.1
Name: github-to-colab-link
Version: 1.0.1
Summary: Generates Google Colab link for jupyter notebooks in public Github repos.
Home-page: https://github.com/ShawonAshraf/github-to-colab-link
Author: Shawon Ashraf
Author-email: shawon13@live.com
License: MIT
Classifier: Programming Language :: Python :: 3.7
Classifier: Operating System :: OS Independent
Requires-Python: >=3.7
License-File: LICENSE
Requires-Dist: autopep8 (==2.0.0)
Requires-Dist: pycodestyle (==2.10.0)
Requires-Dist: tomli (==2.0.1)
